kkba_mathUtils/__init__.py
kkba_mathUtils/area.py
kkba_mathUtils/converter.py
kkba_mathUtils/mathUtils.py
kkba_mathUtils/mean.py
kkba_mathUtils/perimeter.py
kkba_mathUtils-2.0.0.dist-info/LICENCE
kkba_mathUtils-2.0.0.dist-info/METADATA
kkba_mathUtils-2.0.0.dist-info/WHEEL
kkba_mathUtils-2.0.0.dist-info/top_level.txt
kkba_mathUtils-2.0.0.dist-info/RECORD
