Metadata-Version: 2.1
Name: kkba_mathUtils
Version: 2.0.0
Summary: My basic mathematics Python library
Author: Kuate Brayan
Author-email: Kuate Brayan <brayanarmel@gmail.com>
Project-URL: Homepage, https://github.com/KamgaBrayan/KKBA_BASIC_MATH_PYTHON_LIBRARY/tree/main_pypi
Project-URL: Issues, https://github.com/KamgaBrayan/KKBA_BASIC_MATH_PYTHON_LIBRARY/tree/main_pypi
Keywords: mathematics,maths,mean,operations,area,perimeter,arithmetic,quadratic,converter
Classifier: Development Status :: 5 - Production/Stable
Classifier: Intended Audience :: Developers
Classifier: Operating System :: OS Independent
Classifier: License :: OSI Approved :: MIT License
Classifier: Programming Language :: Python :: 3.11
Classifier: Programming Language :: Python :: 3.10
Classifier: Programming Language :: Python :: 3.9
Classifier: Programming Language :: Python :: 3.8
Requires-Python: >=3.8
License-File: LICENCE
